{
  "db_name": "PostgreSQL",
  "query": "\n            SELECT * FROM meme_server_categories\n            WHERE category_id = $1 AND server_id = $2\n            ",
  "describe": {
    "columns": [
      {
        "ordinal": 0,
        "name": "server_id",
        "type_info": "Int8"
      },
      {
        "ordinal": 1,
        "name": "category_id",
        "type_info": "Int4"
      },
      {
        "ordinal": 2,
        "name": "file_id",
        "type_info": "Int4"
      }
    ],
    "parameters": {
      "Left": [
        "Int4",
        "Int8"
      ]
    },
    "nullable": [
      false,
      false,
      false
    ]
  },
  "hash": "a5c55acfb372fc118cb50f65774134ef58f2b6c4e6fecafaa72e08257e130473"
}
